mjv_template/__init__.py
mjv_template-0.2.0.dist-info/LICENSE
mjv_template-0.2.0.dist-info/METADATA
mjv_template-0.2.0.dist-info/WHEEL
mjv_template-0.2.0.dist-info/RECORD
