Metadata-Version: 2.1
Name: mjv-template
Version: 0.2.0
Summary: A template for python projects.
License: MIT
Author: Michael Vogelsong
Author-email: 4020875+mjvogelsong@users.noreply.github.com
Requires-Python: >=3.11,<4.0
Classifier: License :: OSI Approved :: MIT License
Classifier: Programming Language :: Python :: 3
Classifier: Programming Language :: Python :: 3.11
Classifier: Programming Language :: Python :: 3.12
Requires-Dist: pydantic (>=2.6.3,<3.0.0)
